atprotobin/__init__.py
atprotobin/__main__.py
atprotobin/cli.py
atprotobin/server.py
atprotobin/zip_image.py
atprotobin/systemd/atprotobin.service
atprotobin/systemd/caddy-reverse-proxy.service
atprotobin-1.1.2.dist-info/METADATA
atprotobin-1.1.2.dist-info/WHEEL
atprotobin-1.1.2.dist-info/entry_points.txt
atprotobin-1.1.2.dist-info/licenses/LICENSE
atprotobin-1.1.2.dist-info/RECORD
