Metadata-Version: 2.4
Name: atprotobin
Version: 1.1.2
Summary: ATProto based pastebin
Project-URL: Repository, https://github.com/publicdomainrelay/atprotobin.git
Project-URL: Issues, https://github.com/publicdomainrelay/atprotobin/issues
Author-email: Public Domain <publicdomainrelay@protonmail.com>
License: Unlicense
License-File: LICENSE
Requires-Python: >=3.12
Requires-Dist: atproto>=0.0.55
Requires-Dist: fastapi[standard]>=0.115.5
Requires-Dist: markdown2>=2.5.1
Requires-Dist: pillow>=11.0.0
Requires-Dist: pydantic>=2.10.2
Requires-Dist: pygments>=2.18.0
Requires-Dist: python-magic>=0.4.27
Requires-Dist: python-multipart>=0.0.19
Requires-Dist: uvicorn[standard]>=0.32.1
